{
  "rows": [
        {
                            "relId": "Sample-relId-0",
                              "sourceItemId": "Sample-sourceItemId-0",
                              "targetItemId": "Sample-targetItemId-0"
                  }
        ,
            {
                            "relId": "Sample-relId-1",
                              "sourceItemId": "Sample-sourceItemId-1",
                              "targetItemId": "Sample-targetItemId-1"
                  }
        ,
            {
                            "relId": "Sample-relId-2",
                              "sourceItemId": "Sample-sourceItemId-2",
                              "targetItemId": "Sample-targetItemId-2"
                  }
        ,
            {
                            "relId": "Sample-relId-3",
                              "sourceItemId": "Sample-sourceItemId-3",
                              "targetItemId": "Sample-targetItemId-3"
                  }
        ,
            {
                            "relId": "Sample-relId-4",
                              "sourceItemId": "Sample-sourceItemId-4",
                              "targetItemId": "Sample-targetItemId-4"
                  }
        ,
            {
                            "relId": "Sample-relId-5",
                              "sourceItemId": "Sample-sourceItemId-5",
                              "targetItemId": "Sample-targetItemId-5"
                  }
        ,
            {
                            "relId": "Sample-relId-6",
                              "sourceItemId": "Sample-sourceItemId-6",
                              "targetItemId": "Sample-targetItemId-6"
                  }
        ,
            {
                            "relId": "Sample-relId-7",
                              "sourceItemId": "Sample-sourceItemId-7",
                              "targetItemId": "Sample-targetItemId-7"
                  }
        ,
            {
                            "relId": "Sample-relId-8",
                              "sourceItemId": "Sample-sourceItemId-8",
                              "targetItemId": "Sample-targetItemId-8"
                  }
        ,
            {
                            "relId": "Sample-relId-9",
                              "sourceItemId": "Sample-sourceItemId-9",
                              "targetItemId": "Sample-targetItemId-9"
                  }
        ,
            {
                            "relId": "Sample-relId-10",
                              "sourceItemId": "Sample-sourceItemId-10",
                              "targetItemId": "Sample-targetItemId-10"
                  }
        ,
            {
                            "relId": "Sample-relId-11",
                              "sourceItemId": "Sample-sourceItemId-11",
                              "targetItemId": "Sample-targetItemId-11"
                  }
        ,
            {
                            "relId": "Sample-relId-12",
                              "sourceItemId": "Sample-sourceItemId-12",
                              "targetItemId": "Sample-targetItemId-12"
                  }
        ,
            {
                            "relId": "Sample-relId-13",
                              "sourceItemId": "Sample-sourceItemId-13",
                              "targetItemId": "Sample-targetItemId-13"
                  }
          ],
  "totalRecords": 14,
  "lastPage": 2
}